rogue_net/README.md
rogue_net/__init__.py
rogue_net/categorical_action_head.py
rogue_net/embedding.py
rogue_net/input_norm.py
rogue_net/py.typed
rogue_net/ragged_tensor.py
rogue_net/relpos_encoding.py
rogue_net/rogue_net.py
rogue_net/select_entity_action_head.py
rogue_net/test_input_norm.py
rogue_net/tests/test_action_head.py
rogue_net/transformer.py
rogue_net/translate_positions.py
rogue_net-0.1.9.dist-info/WHEEL
rogue_net-0.1.9.dist-info/METADATA
rogue_net-0.1.9.dist-info/RECORD
