Metadata-Version: 2.1
Name: rogue-net
Version: 0.1.9
Summary: Ragged batch transformer implementation that is compatible with entity-gym
Author: Clemens Winter
Author-email: clemenswinter1@gmail.com
Requires-Python: >=3.7.1,<3.11
Classifier: Programming Language :: Python :: 3
Classifier: Programming Language :: Python :: 3.8
Classifier: Programming Language :: Python :: 3.9
Classifier: Programming Language :: Python :: 3.10
Requires-Dist: entity-gym (>=0.1.6,<0.2.0)
Requires-Dist: ragged-buffer (>=0.4.3,<0.5.0)
